setup.py
distributionsGB123/Binomialdistribution.py
distributionsGB123/Gaussiandistribution.py
distributionsGB123/Generaldistribution.py
distributionsGB123/__init__.py
distributionsGB123.egg-info/PKG-INFO
distributionsGB123.egg-info/SOURCES.txt
distributionsGB123.egg-info/dependency_links.txt
distributionsGB123.egg-info/not-zip-safe
distributionsGB123.egg-info/top_level.txt