Metadata-Version: 1.0
Name: distributionsGB123
Version: 1.0
Summary: Gaussian distributions
Home-page: UNKNOWN
Author: Mitul Panchal
Author-email: mitul.panchal72@gmail.com
License: UNKNOWN
Platform: UNKNOWN
